{
  "id": "MAP_SAFFRON_CITY",
  "name": "SaffronCity",
  "layout": "LAYOUT_SAFFRON_CITY",
  "music": "MUS_RG_PEWTER",
  "region_map_section": "MAPSEC_SAFFRON_CITY",
  "requires_flash": false,
  "weather": "WEATHER_NONE",
  "map_type": "MAP_TYPE_TOWN",
  "allow_cycling": false,
  "allow_escaping": false,
  "allow_running": false,
  "show_map_name": true,
  "battle_scene": "MAP_BATTLE_SCENE_NORMAL",
  "connections": [
    {
      "direction": "up",
      "offset": 10,
      "map": "MAP_ROUTE5"
    },
    {
      "direction": "left",
      "offset": 17,
      "map": "MAP_ROUTE7"
    },
    {
      "direction": "right",
      "offset": 17,
      "map": "MAP_ROUTE8"
    },
    {
      "direction": "down",
      "offset": 22,
      "map": "MAP_ROUTE6"
    }
  ],
  "object_events": [

  ],
  "warp_events": [

  ],
  "coord_events": [

  ],
  "bg_events": [

  ]
}
